{
	"info": {
		"_postman_id": "fb53eca0-c8d4-4954-bc9b-dfc981e367b9",
		"name": "City",
		"schema": "https://schema.getpostman.com/json/collection/v2.1.0/collection.json"
	},
	"item": [
		{
			"name": "List",
			"protocolProfileBehavior": {
				"disableBodyPruning": true
			},
			"request": {
				"method": "GET",
				"header": [
					{
						"key": "Accept",
						"value": "application/json",
						"type": "text"
					},
					{
						"key": "Content-Type",
						"name": "Content-Type",
						"value": "application/x-www-form-urlencoded",
						"type": "text"
					}
				],
				"body": {},
				"url": {
					"raw": "{{api}}/v1/cities",
					"host": [
						"{{api}}"
					],
					"path": [
						"v1",
						"cities"
					]
				}
			},
			"response": []
		},
		{
			"name": "Detail",
			"request": {
				"method": "GET",
				"header": [
					{
						"key": "Accept",
						"value": "application/json",
						"type": "text"
					}
				],
				"body": {
					"mode": "raw",
					"raw": ""
				},
				"url": {
					"raw": "{{api}}/v1/cities/1",
					"host": [
						"{{api}}"
					],
					"path": [
						"v1",
						"cities",
						"1"
					]
				}
			},
			"response": []
		},
		{
			"name": "Create",
			"request": {
				"method": "POST",
				"header": [
					{
						"key": "Accept",
						"value": "application/json",
						"type": "text"
					},
					{
						"key": "Content-Type",
						"name": "Content-Type",
						"value": "application/x-www-form-urlencoded",
						"type": "text"
					}
				],
				"body": {
					"mode": "urlencoded",
					"urlencoded": [
						{
							"key": "code",
							"value": "OKKs",
							"type": "text"
						},
						{
							"key": "name",
							"value": "qsdqsd",
							"type": "text"
						},
						{
							"key": "region_id",
							"value": "1",
							"type": "text"
						}
					]
				},
				"url": {
					"raw": "{{api}}/v1/cities",
					"host": [
						"{{api}}"
					],
					"path": [
						"v1",
						"cities"
					]
				}
			},
			"response": []
		},
		{
			"name": "Update",
			"request": {
				"method": "PUT",
				"header": [
					{
						"key": "Accept",
						"value": "application/json",
						"type": "text"
					},
					{
						"key": "Content-Type",
						"name": "Content-Type",
						"value": "application/x-www-form-urlencoded",
						"type": "text"
					}
				],
				"body": {
					"mode": "urlencoded",
					"urlencoded": [
						{
							"key": "code",
							"value": "OKKs",
							"type": "text"
						},
						{
							"key": "name",
							"value": "qsdqsd",
							"type": "text"
						},
						{
							"key": "region_id",
							"value": "1",
							"type": "text"
						}
					]
				},
				"url": {
					"raw": "{{api}}/v1/cities/3",
					"host": [
						"{{api}}"
					],
					"path": [
						"v1",
						"cities",
						"3"
					]
				}
			},
			"response": []
		},
		{
			"name": "Delete",
			"request": {
				"method": "DELETE",
				"header": [
					{
						"key": "Accept",
						"value": "application/json",
						"type": "text"
					}
				],
				"body": {
					"mode": "raw",
					"raw": ""
				},
				"url": {
					"raw": "{{api}}/v1/cities/3",
					"host": [
						"{{api}}"
					],
					"path": [
						"v1",
						"cities",
						"3"
					]
				}
			},
			"response": []
		}
	],
	"auth": {
		"type": "bearer",
		"bearer": [
			{
				"key": "token",
				"value": "{{api_token}}",
				"type": "string"
			}
		]
	},
	"event": [
		{
			"listen": "prerequest",
			"script": {
				"id": "cc3bbbf7-cd58-4eea-ba4d-bd3f10861da6",
				"type": "text/javascript",
				"exec": [
					""
				]
			}
		},
		{
			"listen": "test",
			"script": {
				"id": "b939ceee-b3ca-4ab4-bc30-3aed351df0dc",
				"type": "text/javascript",
				"exec": [
					""
				]
			}
		}
	]
}